xia_engine_postgresql/__init__.py
xia_engine_postgresql/engine.cpython-310-darwin.so
xia_engine_postgresql-0.1.0.dist-info/LICENSE.txt
xia_engine_postgresql-0.1.0.dist-info/METADATA
xia_engine_postgresql-0.1.0.dist-info/WHEEL
xia_engine_postgresql-0.1.0.dist-info/top_level.txt
xia_engine_postgresql-0.1.0.dist-info/RECORD
