Metadata-Version: 2.1
Name: xia-engine-postgresql
Version: 0.1.0
Home-page: https://develop.x-i-a.com/docs/xia-engine-postgresql/0.1.0/index.html
Author: X-I-A
Author-email: admin@x-i-a.com
Requires-Python: >=3.9
License-File: LICENSE.txt
Requires-Dist: psycopg2-binary
Requires-Dist: xia-fields
Requires-Dist: xia-engine
Requires-Dist: xia-engine-sql
